iterframes.abi3.so
iterframes.libs/libavformat-baf965cd.so.58.45.100
iterframes.libs/libxcb-xfixes-6523fc53.so.0.0.0
iterframes.libs/libavdevice-e84807af.so.58.10.100
iterframes.libs/libavutil-82fc4792.so.56.51.100
iterframes.libs/libXau-b2e5323c.so.6.0.0
iterframes.libs/libvpx-ee7f7470.so.6.3.0
iterframes.libs/libxcb-shape-893f3868.so.0.0.0
iterframes.libs/libxcb-77222338.so.1.1.0
iterframes.libs/libbz2-13e8c345.so.1.0.4
iterframes.libs/libswscale-505cdd8e.so.5.7.100
iterframes.libs/libz-eb09ad1d.so.1.2.3
iterframes.libs/libxcb-shm-7ffb2544.so.0.0.0
iterframes.libs/libpostproc-e8f6ad2d.so.55.7.100
iterframes.libs/libx264-99eb0cb0.so.161
iterframes.libs/libavcodec-19fc6e74.so.58.91.100
iterframes.libs/libswresample-83ddd011.so.3.7.100
iterframes.libs/libavfilter-021e10fb.so.7.85.100
iterframes-0.2.0.dist-info/METADATA
iterframes-0.2.0.dist-info/RECORD
iterframes-0.2.0.dist-info/WHEEL
