Metadata-Version: 2.1
Name: iterframes
Version: 0.2.0
Classifier: Intended Audience :: Science/Research
Classifier: Programming Language :: Python :: 3
Classifier: Programming Language :: Python :: Implementation :: CPython
Classifier: Programming Language :: Rust
Classifier: Topic :: Multimedia :: Video
Requires-Dist: numpy>=1.16.0
Summary: Iterate on video frames quickly
Author: Alessio Sanfratello
Requires-Python: >=3.6
